src/design/barrido.sv
module barrido# (
    // number of clk cycles between steps (adjust to change speed)
    parameter int WAIT_TIME = 1,
    // number of columns
    parameter int WIDTH     = 4,
    // set to 1 to make the physical columns active-low (invert output)
    parameter bit ACTIVE_LOW = 1'b0
)(
    input  logic             clk,
    output logic [WIDTH-1:0] col
);

    // simple free-running clock divider / step timer
    int clockCounter = 0;

    // one-hot shift register that holds which column is active
    logic [WIDTH-1:0] col_reg = { { (WIDTH-1){1'b0} }, 1'b1 };

    // rotate the one-hot bit each time clockCounter reaches WAIT_TIME
    always_ff @(posedge clk) begin
        // rotate left: move MSB into LSB
        if (clockCounter >= WAIT_TIME) begin
            clockCounter <= 0;
            //rotate left: move MSB into LSB
            col_reg <= { col_reg[WIDTH-2:0], col_reg[WIDTH-1] };
        end else begin
        clockCounter <= clockCounter + 1;
        end
    end

    // apply active-low if requested
    assign col = ACTIVE_LOW ? ~col_reg : col_reg;

endmodule


module register# (
    // optional instance identifier: users can pass an instance number
    // and WIDTH will default to that value when non-zero.
    parameter int INST_ID = 0,
    // WIDTH can depend on INST_ID; by default use INST_ID when non-zero,
    // otherwise fall back to a sensible default (8).
    parameter int WIDTH = (INST_ID != 0) ? INST_ID : 8
)(
    input  logic             clk,
    input  logic [WIDTH-1:0] d,
    output logic [WIDTH-1:0] q
);

    always_ff @(posedge clk) begin
        q <= d;
    end
endmodule

src/sim/barrido_tb.sv
`timescale 1ns / 1ps


module barrido_tb;

    // Testbench signals
    logic clk;
    // match the DUT width (default WIDTH = 8)
    logic [3:0] col;

    // Instantiate the Unit Under Test (barrido)
    barrido #(1) DUT (
        .clk(clk),
        .col(col)
    );

    // Clock generation
    initial begin
        clk = 0;
        forever #20 clk = ~clk;  // 50 MHz clock (period = 20ns)
    end

    // Simulation control
    initial begin
        // Initialize
        $display("Starting simulation...");
        
        // Wait for some time to observe behavior
        #1000;  // Simulate for a sufficient amount of time to see LED changes

        // End simulation
        $display("Ending simulation...");
        $finish;
    end

    // Monitor LED changes
    initial begin
        $monitor("Time: %0dns, COLUMNA: %b", $time, col);
    end

    initial begin
        $dumpfile("barrido_tb.vcd");  // For waveform viewing
        $dumpvars(0, barrido_tb);
    end

endmodule

src/build/barrido_tb.vcd
$date
	Wed Oct 15 00:03:01 2025
$end
$version
	Icarus Verilog
$end
$timescale
	1ps
$end
$scope module barrido_tb $end
$var wire 4 ! col [3:0] $end
$var reg 1 " clk $end
$scope module DUT $end
$var wire 1 " clk $end
$var wire 4 # col [3:0] $end
$var parameter 1 $ ACTIVE_LOW $end
$var parameter 32 % WAIT_TIME $end
$var parameter 32 & WIDTH $end
$var reg 4 ' col_reg [3:0] $end
$var integer 32 ( clockCounter [31:0] $end
$upscope $end
$upscope $end
$enddefinitions $end
$comment Show the parameter values. $end
$dumpall
b100 &
b1 %
0$
$end
#0
$dumpvars
b0 (
b1 '
b1 #
0"
b1 !
$end
#20000
b1 (
1"
#40000
0"
#60000
b10 !
b10 #
b10 '
b0 (
1"
#80000
0"
#100000
b1 (
1"
#120000
0"
#140000
b100 !
b100 #
b100 '
b0 (
1"
#160000
0"
#180000
b1 (
1"
#200000
0"
#220000
b1000 !
b1000 #
b1000 '
b0 (
1"
#240000
0"
#260000
b1 (
1"
#280000
0"
#300000
b1 !
b1 #
b1 '
b0 (
1"
#320000
0"
#340000
b1 (
1"
#360000
0"
#380000
b10 !
b10 #
b10 '
b0 (
1"
#400000
0"
#420000
b1 (
1"
#440000
0"
#460000
b100 !
b100 #
b100 '
b0 (
1"
#480000
0"
#500000
b1 (
1"
#520000
0"
#540000
b1000 !
b1000 #
b1000 '
b0 (
1"
#560000
0"
#580000
b1 (
1"
#600000
0"
#620000
b1 !
b1 #
b1 '
b0 (
1"
#640000
0"
#660000
b1 (
1"
#680000
0"
#700000
b10 !
b10 #
b10 '
b0 (
1"
#720000
0"
#740000
b1 (
1"
#760000
0"
#780000
b100 !
b100 #
b100 '
b0 (
1"
#800000
0"
#820000
b1 (
1"
#840000
0"
#860000
b1000 !
b1000 #
b1000 '
b0 (
1"
#880000
0"
#900000
b1 (
1"
#920000
0"
#940000
b1 !
b1 #
b1 '
b0 (
1"
#960000
0"
#980000
b1 (
1"
