src/design/barrido.sv
module barrido# (
    // number of clk cycles between steps (adjust to change speed)
    parameter int WAIT_TIME = 1,
    // number of columns
    parameter int WIDTH     = 4,
    // set to 1 to make the physical columns active-low (invert output)
    parameter bit ACTIVE_LOW = 0'b0
)(
    input  logic             clk,
    output logic [WIDTH-1:0] col
);

    // simple free-running clock divider / step timer
    logic clockCounter = 0;

    // one-hot shift register that holds which column is active
    logic [WIDTH-1:0] col_reg = { { (WIDTH-1){1'b0} }, 1'b1 };

    // rotate the one-hot bit each time clockCounter reaches WAIT_TIME
    always_ff @(posedge clk) begin
        //clockCounter <= clockCounter + 1;
            // rotate left: move MSB into LSB
        col_reg <= { col_reg[WIDTH-2:0], col_reg[WIDTH-1] };
        //if (clockCounter >= WAIT_TIME) begin
            //clockCounter <= 0;
            // rotate left: move MSB into LSB
            //col_reg <= { col_reg[WIDTH-2:0], col_reg[WIDTH-1] };
        //end
    end

    // apply active-low if requested
    assign col = ACTIVE_LOW ? ~col_reg : col_reg;

endmodule


module register# (
    // optional instance identifier: users can pass an instance number
    // and WIDTH will default to that value when non-zero.
    parameter int INST_ID = 0,
    // WIDTH can depend on INST_ID; by default use INST_ID when non-zero,
    // otherwise fall back to a sensible default (8).
    parameter int WIDTH = (INST_ID != 0) ? INST_ID : 8
)(
    input  logic             clk,
    input  logic [WIDTH-1:0] d,
    output logic [WIDTH-1:0] q
);

    always_ff @(posedge clk) begin
        q <= d;
    end
endmodule

src/sim/barrido_tb.sv
`timescale 1ns / 1ps


module barrido_tb;

    // Testbench signals
    logic clk;
    // match the DUT width (default WIDTH = 8)
    logic [3:0] col;

    // Instantiate the Unit Under Test (barrido)
    barrido #(135) DUT (
        .clk(clk),
        .col(col)
    );

    // Clock generation
    initial begin
        clk = 0;
        forever #10 clk = ~clk;  // 50 MHz clock (period = 20ns)
    end

    // Simulation control
    initial begin
        // Initialize
        $display("Starting simulation...");
        
        // Wait for some time to observe behavior
        #1000;  // Simulate for a sufficient amount of time to see LED changes

        // End simulation
        $display("Ending simulation...");
        $finish;
    end

    // Monitor LED changes
    initial begin
        $monitor("Time: %0dns, COLUMNA: %b", $time, col);
    end

    initial begin
        $dumpfile("barrido_tb.vcd");  // For waveform viewing
        $dumpvars(0, barrido_tb);
    end

endmodule

src/build/barrido_tb.vcd
$date
	Sun Oct 12 19:20:14 2025
$end
$version
	Icarus Verilog
$end
$timescale
	1ps
$end
$scope module barrido_tb $end
$var wire 4 ! col [3:0] $end
$var reg 1 " clk $end
$scope module DUT $end
$var wire 1 " clk $end
$var wire 4 # col [3:0] $end
$var parameter 1 $ ACTIVE_LOW $end
$var parameter 32 % WAIT_TIME $end
$var parameter 32 & WIDTH $end
$var reg 1 ' clockCounter $end
$var reg 4 ( col_reg [3:0] $end
$upscope $end
$upscope $end
$enddefinitions $end
$comment Show the parameter values. $end
$dumpall
b100 &
b10000111 %
0$
$end
#0
$dumpvars
b1 (
0'
b1 #
0"
b1 !
$end
#10000
b10 !
b10 #
b10 (
1"
#20000
0"
#30000
b100 !
b100 #
b100 (
1"
#40000
0"
#50000
b1000 !
b1000 #
b1000 (
1"
#60000
0"
#70000
b1 !
b1 #
b1 (
1"
#80000
0"
#90000
b10 !
b10 #
b10 (
1"
#100000
0"
#110000
b100 !
b100 #
b100 (
1"
#120000
0"
#130000
b1000 !
b1000 #
b1000 (
1"
#140000
0"
#150000
b1 !
b1 #
b1 (
1"
#160000
0"
#170000
b10 !
b10 #
b10 (
1"
#180000
0"
#190000
b100 !
b100 #
b100 (
1"
#200000
0"
#210000
b1000 !
b1000 #
b1000 (
1"
#220000
0"
#230000
b1 !
b1 #
b1 (
1"
#240000
0"
#250000
b10 !
b10 #
b10 (
1"
#260000
0"
#270000
b100 !
b100 #
b100 (
1"
#280000
0"
#290000
b1000 !
b1000 #
b1000 (
1"
#300000
0"
#310000
b1 !
b1 #
b1 (
1"
#320000
0"
#330000
b10 !
b10 #
b10 (
1"
#340000
0"
#350000
b100 !
b100 #
b100 (
1"
#360000
0"
#370000
b1000 !
b1000 #
b1000 (
1"
#380000
0"
#390000
b1 !
b1 #
b1 (
1"
#400000
0"
#410000
b10 !
b10 #
b10 (
1"
#420000
0"
#430000
b100 !
b100 #
b100 (
1"
#440000
0"
#450000
b1000 !
b1000 #
b1000 (
1"
#460000
0"
#470000
b1 !
b1 #
b1 (
1"
#480000
0"
#490000
b10 !
b10 #
b10 (
1"
#500000
0"
#510000
b100 !
b100 #
b100 (
1"
#520000
0"
#530000
b1000 !
b1000 #
b1000 (
1"
#540000
0"
#550000
b1 !
b1 #
b1 (
1"
#560000
0"
#570000
b10 !
b10 #
b10 (
1"
#580000
0"
#590000
b100 !
b100 #
b100 (
1"
#600000
0"
#610000
b1000 !
b1000 #
b1000 (
1"
#620000
0"
#630000
b1 !
b1 #
b1 (
1"
#640000
0"
#650000
b10 !
b10 #
b10 (
1"
#660000
0"
#670000
b100 !
b100 #
b100 (
1"
#680000
0"
#690000
b1000 !
b1000 #
b1000 (
1"
#700000
0"
#710000
b1 !
b1 #
b1 (
1"
#720000
0"
#730000
b10 !
b10 #
b10 (
1"
#740000
0"
#750000
b100 !
b100 #
b100 (
1"
#760000
0"
#770000
b1000 !
b1000 #
b1000 (
1"
#780000
0"
#790000
b1 !
b1 #
b1 (
1"
#800000
0"
#810000
b10 !
b10 #
b10 (
1"
#820000
0"
#830000
b100 !
b100 #
b100 (
1"
#840000
0"
#850000
b1000 !
b1000 #
b1000 (
1"
#860000
0"
#870000
b1 !
b1 #
b1 (
1"
#880000
0"
#890000
b10 !
b10 #
b10 (
1"
#900000
0"
#910000
b100 !
b100 #
b100 (
1"
#920000
0"
#930000
b1000 !
b1000 #
b1000 (
1"
#940000
0"
#950000
b1 !
b1 #
b1 (
1"
#960000
0"
#970000
b10 !
b10 #
b10 (
1"
#980000
0"
#990000
b100 !
b100 #
b100 (
1"
