src/design/sizes_pkg.sv
// sizes_pkg.sv
// Centralized package for register widths used by the system.

package sizes_pkg;

    // Default register widths for different channels/elements in the system.
    // Users can edit these constants to change sizes across the whole system.
    // Alternatively, these can be overridden at compile/synthesis time.
    localparam int REG_WIDTH_0 = 8;   // default width for register 0
    localparam int REG_WIDTH_1 = 16;  // default width for register 1
    localparam int REG_WIDTH_2 = 4;   // default width for register 2
    localparam int REG_WIDTH_3 = 32;  // default width for register 3

endpackage : sizes_pkg

src/design/barrido.sv
module barrido# (
    // number of clk cycles between steps (adjust to change speed)
    parameter int WAIT_TIME = 10,
    // number of columns
    parameter int WIDTH     = 4,
    // set to 1 to make the physical columns active-low (invert output)
    parameter bit ACTIVE_LOW = 1'b0
)(
    input  logic             clk,
    output logic [WIDTH-1:0] col
);

    // simple free-running clock divider / step timer
    int clockCounter = 0;

    // one-hot shift register that holds which column is active
    logic [WIDTH-1:0] col_reg = { { (WIDTH-1){1'b0} }, 1'b1 };

    // rotate the one-hot bit each time clockCounter reaches WAIT_TIME
    always_ff @(posedge clk) begin
        // rotate left: move MSB into LSB
        if (clockCounter >= WAIT_TIME) begin
            clockCounter <= 0;
            //rotate left: move MSB into LSB
            col_reg <= { col_reg[WIDTH-2:0], col_reg[WIDTH-1] };
        end else begin
        clockCounter <= clockCounter + 1;
        end
    end

    // apply active-low if requested
    assign col = ACTIVE_LOW ? ~col_reg : col_reg;

endmodule


module register# (
    // optional instance identifier: users can pass an instance number
    // and WIDTH will default to that value when non-zero.
    parameter int INST_ID = 0,
    // WIDTH can depend on INST_ID; by default use INST_ID when non-zero,
    // otherwise fall back to a sensible default (8).
    parameter int WIDTH = (INST_ID != 0) ? INST_ID : 8
)(
    input  logic             clk,
    input  logic [WIDTH-1:0] d,
    output logic [WIDTH-1:0] q
);

    always_ff @(posedge clk) begin
        q <= d;
    end
endmodule

src/design/sistema_de_lectura.sv
// sistema_de_lectura.sv
// Módulo de sistema de nivel superior que demuestra el uso de registros de diferentes tamaños
// y el módulo `barrido` existente.

//`include "sizes_pkg.sv"

module sistema_de_lectura #(
    parameter int WIDTH = 4,
    parameter int DEBOUNCE_PULSES = 3
)(
    input  logic              clk,
    output logic [WIDTH-1:0]  col,
    input  logic  [WIDTH-1:0] fil,
    // nueva interfaz de captura
    output logic [WIDTH-1:0]  pressed_col_out, // salida one-hot de la última columna aceptada
    output logic [WIDTH-1:0]  pressed_row_out, // salida one-hot de la última fila aceptada
    output logic              pressed_valid,   // activa cuando hay una pulsación capturada disponible
    input  logic              ack_read,        // el consumidor pulsa esto para limpiar pressed_valid
    output integer                numero,
    output logic              reset,
    output logic              save
);

    // barrido de columnas
    barrido #(.WIDTH(WIDTH)) barrido (
        .clk(clk),
        .col(col)
    );

    // --- sincronizar entradas en bruto al dominio de clk (2 etapas) ---
    logic [WIDTH-1:0] fil_sync1, fil_sync2, fil_prev;
    always_ff @(posedge clk) begin
        fil_sync1 <= fil;
        fil_sync2 <= fil_sync1;
        fil_prev  <= fil_sync2;
    end

    // detección de flancos (flancos ascendentes en filas)
    logic [WIDTH-1:0] fil_rise;
    assign fil_rise = fil_sync2 & ~fil_prev;

    // --- captura de pulsación + antirrebote entre rotaciones ---
    logic                press_pending = 1'b0;
    logic [WIDTH-1:0]    pressed_row_oh;
    logic [WIDTH-1:0]    pressed_col_oh;      // instantánea de col en la primera detección
    int unsigned         confirm_count = 0;

    // salidas / estado
    logic                debounced_event;
    logic [WIDTH-1:0]    last_pressed_col;
    logic [WIDTH-1:0]    last_pressed_row;

    // inicializar salidas de captura
    initial begin
        pressed_col_out = '0;
        pressed_row_out = '0;
        pressed_valid   = 1'b0;
        numero = 0;
        reset = 1'b0;
        save = 1'b0;
    end

    always_ff @(posedge clk) begin
        debounced_event <= 1'b0;

        if (!press_pending) begin
            if (|fil_rise) begin
                // capturar qué fila subió y qué columna estaba activa en ese momento
                press_pending    <= 1'b1;
                pressed_row_oh   <= fil_rise;
                pressed_col_oh   <= col;
                confirm_count    <= 0;
            end
        end else begin
            // cuando la columna capturada aparece, verificar la entrada de fila
            if (|(pressed_col_oh & col)) begin
                if (|(pressed_row_oh & fil_sync2)) begin
                    // confirmación: en esta visita de columna la fila lee alto
                    confirm_count <= confirm_count + 1;
                    if (confirm_count + 1 >= DEBOUNCE_PULSES) begin
                        // pulsación aceptada después del antirrebote
                        debounced_event   <= 1'b1;
                        last_pressed_col  <= pressed_col_oh;
                        last_pressed_row  <= pressed_row_oh;
                        press_pending     <= 1'b0;
                        confirm_count     <= 0;

                        // activar hacia afuera (solo si el consumidor no ha leído el anterior)
                        if (!pressed_valid) begin
                            pressed_col_out <= pressed_col_oh;
                            pressed_row_out <= pressed_row_oh;
                            pressed_valid   <= 1'b1;
                        end
                    end
                end else begin
                    // confirmación fallida para esta visita -> resetear contador y seguir esperando
                    confirm_count <= 0;
                end
            end

            // opcional: si la fila se libera completamente antes de la confirmación, cancelar
            if (!(|(
                pressed_row_oh & fil_sync2
            ))) begin
                // si la fila está estable en bajo por un período largo puedes cancelar;
                // dejado simple: solo limpiamos en aceptación explícita o lógica externa
            end
        end

        // ack limpia valid (síncrono)
        if (ack_read)
            pressed_valid <= 1'b0;
    end
    
    always_ff @(posedge clk) begin
        // Resetear banderas por defecto
    //    reset <= 1'b0;
    //    save <= 1'b0;
        
        if (debounced_event) begin
            case({pressed_col_oh, pressed_row_oh})
                8'b1000_1000 : numero <= 1; // columna 0, fila 0 = 1
                8'b0100_1000 : numero <= 2; // columna 1, fila 0 = 2
                8'b0010_1000 : numero <= 3; // columna 2, fila 0 = 3

                8'b1000_0100 : numero <= 4; // columna 0, fila 1 = 4
                8'b0100_0100 : numero <= 5; // columna 1, fila 1 = 5
                8'b0010_0100 : numero <= 6; // columna 2, fila 1 = 6

                8'b1000_0010 : numero <= 7; // columna 0, fila 2 = 7
                8'b0100_0010 : numero <= 8; // columna 1, fila 2 = 8
                8'b0010_0010 : numero <= 9; // columna 2, fila 2 = 9

                8'b1000_0001 : reset <= 1'b1; // columna 0, fila 3 = * 
                8'b0100_0001 : numero <= 0; // columna 1, fila 3 = 0
                8'b0010_0001 : save <= 1'b1; // columna 2, fila 3 = # 
                default      : begin
                    // No hay acción para combinaciones inválidas
                end
            endcase
        end
        // Solo actualizar cuando se detecta una pulsación válida
    end
    // (opcional) exponer debounced_event como salida o conectar a otra lógica
    // ...código existente...
endmodule

src/sim/sistema_de_lectura_tb.sv
`timescale 1ns / 1ps

module sistema_de_lectura_tb;

    localparam WIDTH = 4;
    localparam DB_PULSES = 3;

    reg                 clk;
    reg  [WIDTH-1:0]    fil;
    wire [WIDTH-1:0]    col;
    wire [WIDTH-1:0]    pressed_col_out;
    wire [WIDTH-1:0]    pressed_row_out;
    wire                pressed_valid;
    reg                 ack_read;

    // conteos usados por el stimulus: declarar en ámbito de módulo (portátil)
    integer long_hold;
    integer medium_hold;
    integer short_hold;

    // señales expuestas por el DUT
    wire integer    numero;
    wire            reset;
    wire            save;

    // Instantiate DUT
    sistema_de_lectura #(
        .WIDTH(WIDTH),
        .DEBOUNCE_PULSES(DB_PULSES)
    ) DUT (
        .clk(clk),
        .col(col),
        .fil(fil),
        .pressed_col_out(pressed_col_out),
        .pressed_row_out(pressed_row_out),
        .pressed_valid(pressed_valid),
        .ack_read(ack_read),
        .numero(numero),
        .reset(reset),
        .save(save)
    );

    // clock 50 MHz -> period 20 ns
    initial begin
        clk = 0;
        forever #10 clk = ~clk;
    end

    // waveform dump and header
    initial begin
        $dumpfile("sistema_de_lectura_tb.vcd");
        $dumpvars(0, sistema_de_lectura_tb);
        $display("TIME(ns)\tcol    fil    pcol   prow   valid   numero reset save");
    end

    // print registers and signals every clock edge
    always @(posedge clk) begin
        $display("%0t\t%b %b %b %b %b    %0d     %b    %b",
                 $time, col, fil, pressed_col_out, pressed_row_out, pressed_valid,
                 numero, reset, save);
    end

    // helper task
    task press_at_col(input integer row, input integer col_idx, input integer hold_cycles);
        reg [WIDTH-1:0] target;
        reg [WIDTH-1:0] target_row;
        integer i;
    begin
        target = {WIDTH{1'b0}};
        for (i = 0; i < WIDTH; i = i + 1) target[i] = (i == col_idx) ? 1'b1 : 1'b0;
        @(posedge clk);
        while (col !== target) @(posedge clk);
        target_row = {WIDTH{1'b0}};
        for (i = 0; i < WIDTH; i = i + 1) target_row[i] = (i == row) ? 1'b1 : 1'b0;
        fil = target_row;
        $display("TB: assert fil row=%0d at %0t (col target=%b)", row, $time, target);
        repeat (hold_cycles) @(posedge clk);
        fil = {WIDTH{1'b0}};
        @(posedge clk);
        $display("TB: release fil row=%0d at %0t", row, $time);
    end
    endtask

    // stimulus
    initial begin
        ack_read = 0;
        fil = {WIDTH{1'b0}};
        repeat (10) @(posedge clk);

        // inicializar contadores
        long_hold   = 100;
        medium_hold = 40;
        short_hold  = 10;

        press_at_col(2, 0, long_hold);
        repeat (50) @(posedge clk);
        if (pressed_valid) begin
            $display("TB: latched -> pcol=%b prow=%b numero=%0d reset=%b save=%b at %0t",
                     pressed_col_out, pressed_row_out, numero, reset, save, $time);
            ack_read = 1;
            @(posedge clk);
            ack_read = 0;
        end

        press_at_col(0, 0, medium_hold);
        repeat (50) @(posedge clk);
        if (pressed_valid) begin
            $display("TB: latched -> pcol=%b prow=%b numero=%0d reset=%b save=%b at %0t",
                     pressed_col_out, pressed_row_out, numero, reset, save, $time);
            ack_read = 1; @(posedge clk); ack_read = 0;
        end

        // finish
        repeat (50) @(posedge clk);
        $display("Testbench finished at %0t", $time);
        $finish;
    end

    // safety timeout (separate initial)
    initial begin
        #5000000;
        $display("TB: timeout at %0t", $time);
        $finish;
    end

endmodule

src/build/sistema_de_lectura_tb.vcd
$date
	Tue Oct 21 11:42:17 2025
$end
$version
	Icarus Verilog
$end
$timescale
	1ps
$end
$scope module sistema_de_lectura_tb $end
$var wire 1 ! save $end
$var wire 1 " reset $end
$var wire 1 # pressed_valid $end
$var wire 4 $ pressed_row_out [3:0] $end
$var wire 4 % pressed_col_out [3:0] $end
$var wire 32 & numero [31:0] $end
$var wire 4 ' col [3:0] $end
$var parameter 32 ( DB_PULSES $end
$var parameter 32 ) WIDTH $end
$var reg 1 * ack_read $end
$var reg 1 + clk $end
$var reg 4 , fil [3:0] $end
$var integer 32 - long_hold [31:0] $end
$var integer 32 . medium_hold [31:0] $end
$var integer 32 / short_hold [31:0] $end
$scope module DUT $end
$var wire 1 * ack_read $end
$var wire 1 + clk $end
$var wire 4 0 fil [3:0] $end
$var wire 4 1 fil_rise [3:0] $end
$var wire 4 2 col [3:0] $end
$var parameter 32 3 DEBOUNCE_PULSES $end
$var parameter 32 4 WIDTH $end
$var reg 1 5 debounced_event $end
$var reg 4 6 fil_prev [3:0] $end
$var reg 4 7 fil_sync1 [3:0] $end
$var reg 4 8 fil_sync2 [3:0] $end
$var reg 4 9 last_pressed_col [3:0] $end
$var reg 4 : last_pressed_row [3:0] $end
$var reg 1 ; press_pending $end
$var reg 4 < pressed_col_oh [3:0] $end
$var reg 4 = pressed_col_out [3:0] $end
$var reg 4 > pressed_row_oh [3:0] $end
$var reg 4 ? pressed_row_out [3:0] $end
$var reg 1 # pressed_valid $end
$var reg 1 " reset $end
$var reg 1 ! save $end
$var reg 32 @ confirm_count [31:0] $end
$var integer 32 A numero [31:0] $end
$scope module barrido $end
$var wire 1 + clk $end
$var wire 4 B col [3:0] $end
$var parameter 1 C ACTIVE_LOW $end
$var parameter 32 D WAIT_TIME $end
$var parameter 32 E WIDTH $end
$var reg 4 F col_reg [3:0] $end
$var integer 32 G clockCounter [31:0] $end
$upscope $end
$upscope $end
$scope task press_at_col $end
$var reg 4 H target [3:0] $end
$var reg 4 I target_row [3:0] $end
$var integer 32 J col_idx [31:0] $end
$var integer 32 K hold_cycles [31:0] $end
$var integer 32 L i [31:0] $end
$var integer 32 M row [31:0] $end
$upscope $end
$upscope $end
$enddefinitions $end
$comment Show the parameter values. $end
$dumpall
b100 E
b1010 D
0C
b100 4
b11 3
b100 )
b11 (
$end
#0
$dumpvars
bx M
bx L
bx K
bx J
bx I
bx H
b0 G
b1 F
b1 B
b0 A
b0 @
b0 ?
bx >
b0 =
bx <
0;
bx :
bx 9
bx 8
bx 7
bx 6
x5
b1 2
bx 1
b0 0
bx /
bx .
bx -
b0 ,
0+
0*
b1 '
b0 &
b0 %
b0 $
0#
0"
0!
$end
#10000
b1 G
b0 7
05
1+
#20000
0+
#30000
b0 1
b0 8
b10 G
1+
#40000
0+
#50000
b11 G
b0 6
1+
#60000
0+
#70000
b100 G
1+
#80000
0+
#90000
b101 G
1+
#100000
0+
#110000
b110 G
1+
#120000
0+
#130000
b111 G
1+
#140000
0+
#150000
b1000 G
1+
#160000
0+
#170000
b1001 G
1+
#180000
0+
#190000
b1010 G
b100 L
b1 H
b1100100 K
b0 J
b10 M
b1010 /
b101000 .
b1100100 -
1+
#200000
0+
#210000
b10 '
b10 2
b10 B
b10 F
b0 G
b100 7
b100 ,
b100 0
b100 L
b100 I
1+
#220000
0+
#230000
b100 1
b100 8
b1 G
1+
#240000
0+
#250000
b0 1
b10 G
b100 6
b10 <
b100 >
1;
1+
#260000
0+
#270000
b1 @
b11 G
1+
#280000
0+
#290000
b100 G
b10 @
1+
#300000
0+
#310000
1#
b100 $
b100 ?
b10 %
b10 =
0;
b100 :
b10 9
15
b0 @
b101 G
1+
#320000
0+
#330000
b110 G
05
b110 &
b110 A
1+
#340000
0+
#350000
b111 G
1+
#360000
0+
#370000
b1000 G
1+
#380000
0+
#390000
b1001 G
1+
#400000
0+
#410000
b1010 G
1+
#420000
0+
#430000
b100 '
b100 2
b100 B
b100 F
b0 G
1+
#440000
0+
#450000
b1 G
1+
#460000
0+
#470000
b10 G
1+
#480000
0+
#490000
b11 G
1+
#500000
0+
#510000
b100 G
1+
#520000
0+
#530000
b101 G
1+
#540000
0+
#550000
b110 G
1+
#560000
0+
#570000
b111 G
1+
#580000
0+
#590000
b1000 G
1+
#600000
0+
#610000
b1001 G
1+
#620000
0+
#630000
b1010 G
1+
#640000
0+
#650000
b1000 '
b1000 2
b1000 B
b1000 F
b0 G
1+
#660000
0+
#670000
b1 G
1+
#680000
0+
#690000
b10 G
1+
#700000
0+
#710000
b11 G
1+
#720000
0+
#730000
b100 G
1+
#740000
0+
#750000
b101 G
1+
#760000
0+
#770000
b110 G
1+
#780000
0+
#790000
b111 G
1+
#800000
0+
#810000
b1000 G
1+
#820000
0+
#830000
b1001 G
1+
#840000
0+
#850000
b1010 G
1+
#860000
0+
#870000
b1 '
b1 2
b1 B
b1 F
b0 G
1+
#880000
0+
#890000
b1 G
1+
#900000
0+
#910000
b10 G
1+
#920000
0+
#930000
b11 G
1+
#940000
0+
#950000
b100 G
1+
#960000
0+
#970000
b101 G
1+
#980000
0+
#990000
b110 G
1+
#1000000
0+
#1010000
b111 G
1+
#1020000
0+
#1030000
b1000 G
1+
#1040000
0+
#1050000
b1001 G
1+
#1060000
0+
#1070000
b1010 G
1+
#1080000
0+
#1090000
b10 '
b10 2
b10 B
b10 F
b0 G
1+
#1100000
0+
#1110000
b1 G
1+
#1120000
0+
#1130000
b10 G
1+
#1140000
0+
#1150000
b11 G
1+
#1160000
0+
#1170000
b100 G
1+
#1180000
0+
#1190000
b101 G
1+
#1200000
0+
#1210000
b110 G
1+
#1220000
0+
#1230000
b111 G
1+
#1240000
0+
#1250000
b1000 G
1+
#1260000
0+
#1270000
b1001 G
1+
#1280000
0+
#1290000
b1010 G
1+
#1300000
0+
#1310000
b100 '
b100 2
b100 B
b100 F
b0 G
1+
#1320000
0+
#1330000
b1 G
1+
#1340000
0+
#1350000
b10 G
1+
#1360000
0+
#1370000
b11 G
1+
#1380000
0+
#1390000
b100 G
1+
#1400000
0+
#1410000
b101 G
1+
#1420000
0+
#1430000
b110 G
1+
#1440000
0+
#1450000
b111 G
1+
#1460000
0+
#1470000
b1000 G
1+
#1480000
0+
#1490000
b1001 G
1+
#1500000
0+
#1510000
b1010 G
1+
#1520000
0+
#1530000
b1000 '
b1000 2
b1000 B
b1000 F
b0 G
1+
#1540000
0+
#1550000
b1 G
1+
#1560000
0+
#1570000
b10 G
1+
#1580000
0+
#1590000
b11 G
1+
#1600000
0+
#1610000
b100 G
1+
#1620000
0+
#1630000
b101 G
1+
#1640000
0+
#1650000
b110 G
1+
#1660000
0+
#1670000
b111 G
1+
#1680000
0+
#1690000
b1000 G
1+
#1700000
0+
#1710000
b1001 G
1+
#1720000
0+
#1730000
b1010 G
1+
#1740000
0+
#1750000
b1 '
b1 2
b1 B
b1 F
b0 G
1+
#1760000
0+
#1770000
b1 G
1+
#1780000
0+
#1790000
b10 G
1+
#1800000
0+
#1810000
b11 G
1+
#1820000
0+
#1830000
b100 G
1+
#1840000
0+
#1850000
b101 G
1+
#1860000
0+
#1870000
b110 G
1+
#1880000
0+
#1890000
b111 G
1+
#1900000
0+
#1910000
b1000 G
1+
#1920000
0+
#1930000
b1001 G
1+
#1940000
0+
#1950000
b1010 G
1+
#1960000
0+
#1970000
b10 '
b10 2
b10 B
b10 F
b0 G
1+
#1980000
0+
#1990000
b1 G
1+
#2000000
0+
#2010000
b10 G
1+
#2020000
0+
#2030000
b11 G
1+
#2040000
0+
#2050000
b100 G
1+
#2060000
0+
#2070000
b101 G
1+
#2080000
0+
#2090000
b110 G
1+
#2100000
0+
#2110000
b111 G
1+
#2120000
0+
#2130000
b1000 G
1+
#2140000
0+
#2150000
b1001 G
1+
#2160000
0+
#2170000
b1010 G
1+
#2180000
0+
#2190000
b100 '
b100 2
b100 B
b100 F
b0 G
1+
#2200000
0+
#2210000
b1 G
b0 7
b0 ,
b0 0
1+
#2220000
0+
#2230000
b0 8
b10 G
1+
#2240000
0+
#2250000
b11 G
b0 6
1+
#2260000
0+
#2270000
b100 G
1+
#2280000
0+
#2290000
b101 G
1+
#2300000
0+
#2310000
b110 G
1+
#2320000
0+
#2330000
b111 G
1+
#2340000
0+
#2350000
b1000 G
1+
#2360000
0+
#2370000
b1001 G
1+
#2380000
0+
#2390000
b1010 G
1+
#2400000
0+
#2410000
b1000 '
b1000 2
b1000 B
b1000 F
b0 G
1+
#2420000
0+
#2430000
b1 G
1+
#2440000
0+
#2450000
b10 G
1+
#2460000
0+
#2470000
b11 G
1+
#2480000
0+
#2490000
b100 G
1+
#2500000
0+
#2510000
b101 G
1+
#2520000
0+
#2530000
b110 G
1+
#2540000
0+
#2550000
b111 G
1+
#2560000
0+
#2570000
b1000 G
1+
#2580000
0+
#2590000
b1001 G
1+
#2600000
0+
#2610000
b1010 G
1+
#2620000
0+
#2630000
b1 '
b1 2
b1 B
b1 F
b0 G
1+
#2640000
0+
#2650000
b1 G
1+
#2660000
0+
#2670000
b10 G
1+
#2680000
0+
#2690000
b11 G
1+
#2700000
0+
#2710000
b100 G
1+
#2720000
0+
#2730000
b101 G
1+
#2740000
0+
#2750000
b110 G
1+
#2760000
0+
#2770000
b111 G
1+
#2780000
0+
#2790000
b1000 G
1+
#2800000
0+
#2810000
b1001 G
1+
#2820000
0+
#2830000
b1010 G
1+
#2840000
0+
#2850000
b10 '
b10 2
b10 B
b10 F
b0 G
1+
#2860000
0+
#2870000
b1 G
1+
#2880000
0+
#2890000
b10 G
1+
#2900000
0+
#2910000
b11 G
1+
#2920000
0+
#2930000
b100 G
1+
#2940000
0+
#2950000
b101 G
1+
#2960000
0+
#2970000
b110 G
1+
#2980000
0+
#2990000
b111 G
1+
#3000000
0+
#3010000
b1000 G
1+
#3020000
0+
#3030000
b1001 G
1+
#3040000
0+
#3050000
b1010 G
1+
#3060000
0+
#3070000
b100 '
b100 2
b100 B
b100 F
b0 G
1+
#3080000
0+
#3090000
b1 G
1+
#3100000
0+
#3110000
b10 G
1+
#3120000
0+
#3130000
b11 G
1+
#3140000
0+
#3150000
b100 G
1+
#3160000
0+
#3170000
b101 G
1+
#3180000
0+
#3190000
b110 G
1+
#3200000
0+
#3210000
b111 G
1+
#3220000
0+
#3230000
b1000 G
1*
1+
#3240000
0+
#3250000
b1001 G
b100 L
b1 H
b101000 K
b0 M
0*
1+
#3260000
0+
#3270000
b1010 G
1+
#3280000
0+
#3290000
b1000 '
b1000 2
b1000 B
b1000 F
b0 G
1+
#3300000
0+
#3310000
b1 G
1+
#3320000
0+
#3330000
b10 G
1+
#3340000
0+
#3350000
b11 G
1+
#3360000
0+
#3370000
b100 G
1+
#3380000
0+
#3390000
b101 G
1+
#3400000
0+
#3410000
b110 G
1+
#3420000
0+
#3430000
b111 G
1+
#3440000
0+
#3450000
b1000 G
1+
#3460000
0+
#3470000
b1001 G
1+
#3480000
0+
#3490000
b1010 G
1+
#3500000
0+
#3510000
b1 '
b1 2
b1 B
b1 F
b0 G
1+
#3520000
0+
#3530000
b1 G
b1 ,
b1 0
b100 L
b1 I
1+
#3540000
0+
#3550000
b1 7
b10 G
1+
#3560000
0+
#3570000
b1 1
b11 G
b1 8
1+
#3580000
0+
#3590000
b0 1
b1 <
b1 >
1;
b1 6
b100 G
1+
#3600000
0+
#3610000
b101 G
b1 @
1+
#3620000
0+
#3630000
b10 @
b110 G
1+
#3640000
0+
#3650000
b111 G
0;
b1 :
b1 9
15
b0 @
1+
#3660000
0+
#3670000
05
b1000 G
1+
#3680000
0+
#3690000
b1001 G
1+
#3700000
0+
#3710000
b1010 G
1+
#3720000
0+
#3730000
b10 '
b10 2
b10 B
b10 F
b0 G
1+
#3740000
0+
#3750000
b1 G
1+
#3760000
0+
#3770000
b10 G
1+
#3780000
0+
#3790000
b11 G
1+
#3800000
0+
#3810000
b100 G
1+
#3820000
0+
#3830000
b101 G
1+
#3840000
0+
#3850000
b110 G
1+
#3860000
0+
#3870000
b111 G
1+
#3880000
0+
#3890000
b1000 G
1+
#3900000
0+
#3910000
b1001 G
1+
#3920000
0+
#3930000
b1010 G
1+
#3940000
0+
#3950000
b100 '
b100 2
b100 B
b100 F
b0 G
1+
#3960000
0+
#3970000
b1 G
1+
#3980000
0+
#3990000
b10 G
1+
#4000000
0+
#4010000
b11 G
1+
#4020000
0+
#4030000
b100 G
1+
#4040000
0+
#4050000
b101 G
1+
#4060000
0+
#4070000
b110 G
1+
#4080000
0+
#4090000
b111 G
1+
#4100000
0+
#4110000
b1000 G
1+
#4120000
0+
#4130000
b1001 G
1+
#4140000
0+
#4150000
b1010 G
1+
#4160000
0+
#4170000
b1000 '
b1000 2
b1000 B
b1000 F
b0 G
1+
#4180000
0+
#4190000
b1 G
1+
#4200000
0+
#4210000
b10 G
1+
#4220000
0+
#4230000
b11 G
1+
#4240000
0+
#4250000
b100 G
1+
#4260000
0+
#4270000
b101 G
1+
#4280000
0+
#4290000
b110 G
1+
#4300000
0+
#4310000
b111 G
1+
#4320000
0+
#4330000
b1000 G
b0 ,
b0 0
1+
#4340000
0+
#4350000
b0 7
b1001 G
1+
#4360000
0+
#4370000
b1010 G
b0 8
1+
#4380000
0+
#4390000
b0 6
b1 '
b1 2
b1 B
b1 F
b0 G
1+
#4400000
0+
#4410000
b1 G
1+
#4420000
0+
#4430000
b10 G
1+
#4440000
0+
#4450000
b11 G
1+
#4460000
0+
#4470000
b100 G
1+
#4480000
0+
#4490000
b101 G
1+
#4500000
0+
#4510000
b110 G
1+
#4520000
0+
#4530000
b111 G
1+
#4540000
0+
#4550000
b1000 G
1+
#4560000
0+
#4570000
b1001 G
1+
#4580000
0+
#4590000
b1010 G
1+
#4600000
0+
#4610000
b10 '
b10 2
b10 B
b10 F
b0 G
1+
#4620000
0+
#4630000
b1 G
1+
#4640000
0+
#4650000
b10 G
1+
#4660000
0+
#4670000
b11 G
1+
#4680000
0+
#4690000
b100 G
1+
#4700000
0+
#4710000
b101 G
1+
#4720000
0+
#4730000
b110 G
1+
#4740000
0+
#4750000
b111 G
1+
#4760000
0+
#4770000
b1000 G
1+
#4780000
0+
#4790000
b1001 G
1+
#4800000
0+
#4810000
b1010 G
1+
#4820000
0+
#4830000
b100 '
b100 2
b100 B
b100 F
b0 G
1+
#4840000
0+
#4850000
b1 G
1+
#4860000
0+
#4870000
b10 G
1+
#4880000
0+
#4890000
b11 G
1+
#4900000
0+
#4910000
b100 G
1+
#4920000
0+
#4930000
b101 G
1+
#4940000
0+
#4950000
b110 G
1+
#4960000
0+
#4970000
b111 G
1+
#4980000
0+
#4990000
b1000 G
1+
#5000000
0+
#5010000
b1001 G
1+
#5020000
0+
#5030000
b1010 G
1+
#5040000
0+
#5050000
b1000 '
b1000 2
b1000 B
b1000 F
b0 G
1+
#5060000
0+
#5070000
b1 G
1+
#5080000
0+
#5090000
b10 G
1+
#5100000
0+
#5110000
b11 G
1+
#5120000
0+
#5130000
b100 G
1+
#5140000
0+
#5150000
b101 G
1+
#5160000
0+
#5170000
b110 G
1+
#5180000
0+
#5190000
b111 G
1+
#5200000
0+
#5210000
b1000 G
1+
#5220000
0+
#5230000
b1001 G
1+
#5240000
0+
#5250000
b1010 G
1+
#5260000
0+
#5270000
b1 '
b1 2
b1 B
b1 F
b0 G
1+
#5280000
0+
#5290000
b1 G
1+
#5300000
0+
#5310000
b10 G
1+
#5320000
0+
#5330000
b11 G
1+
#5340000
0+
#5350000
b100 G
1*
1+
#5360000
0+
#5370000
b101 G
0*
1+
#5380000
0+
#5390000
b110 G
1+
#5400000
0+
#5410000
b111 G
1+
#5420000
0+
#5430000
b1000 G
1+
#5440000
0+
#5450000
b1001 G
1+
#5460000
0+
#5470000
b1010 G
1+
#5480000
0+
#5490000
b10 '
b10 2
b10 B
b10 F
b0 G
1+
#5500000
0+
#5510000
b1 G
1+
#5520000
0+
#5530000
b10 G
1+
#5540000
0+
#5550000
b11 G
1+
#5560000
0+
#5570000
b100 G
1+
#5580000
0+
#5590000
b101 G
1+
#5600000
0+
#5610000
b110 G
1+
#5620000
0+
#5630000
b111 G
1+
#5640000
0+
#5650000
b1000 G
1+
#5660000
0+
#5670000
b1001 G
1+
#5680000
0+
#5690000
b1010 G
1+
#5700000
0+
#5710000
b100 '
b100 2
b100 B
b100 F
b0 G
1+
#5720000
0+
#5730000
b1 G
1+
#5740000
0+
#5750000
b10 G
1+
#5760000
0+
#5770000
b11 G
1+
#5780000
0+
#5790000
b100 G
1+
#5800000
0+
#5810000
b101 G
1+
#5820000
0+
#5830000
b110 G
1+
#5840000
0+
#5850000
b111 G
1+
#5860000
0+
#5870000
b1000 G
1+
#5880000
0+
#5890000
b1001 G
1+
#5900000
0+
#5910000
b1010 G
1+
#5920000
0+
#5930000
b1000 '
b1000 2
b1000 B
b1000 F
b0 G
1+
#5940000
0+
#5950000
b1 G
1+
#5960000
0+
#5970000
b10 G
1+
#5980000
0+
#5990000
b11 G
1+
#6000000
0+
#6010000
b100 G
1+
#6020000
0+
#6030000
b101 G
1+
#6040000
0+
#6050000
b110 G
1+
#6060000
0+
#6070000
b111 G
1+
#6080000
0+
#6090000
b1000 G
1+
#6100000
0+
#6110000
b1001 G
1+
#6120000
0+
#6130000
b1010 G
1+
#6140000
0+
#6150000
b1 '
b1 2
b1 B
b1 F
b0 G
1+
#6160000
0+
#6170000
b1 G
1+
#6180000
0+
#6190000
b10 G
1+
#6200000
0+
#6210000
b11 G
1+
#6220000
0+
#6230000
b100 G
1+
#6240000
0+
#6250000
b101 G
1+
#6260000
0+
#6270000
b110 G
1+
#6280000
0+
#6290000
b111 G
1+
#6300000
0+
#6310000
b1000 G
1+
#6320000
0+
#6330000
b1001 G
1+
#6340000
0+
#6350000
b1010 G
1+
#6360000
0+
#6370000
b10 '
b10 2
b10 B
b10 F
b0 G
1+
